{
  "format": "Instagram 1080x1080",
  "style": "editorial clair institutionnel",
  "objet": "Présenter l’objet de l’association TVF",
  "caption": "Territoires Vivants France a pour objet de remettre en usage les lieux, biens et ressources inutilisés grâce à la coopération territoriale : logements vacants, commerces fermés, friches, terrains, bâtiments et matériaux réemployables. Depuis Saint-Étienne, TVF construit une démarche nationale utile aux habitants et aux territoires.",
  "hashtags": [
    "#TerritoiresVivantsFrance",
    "#SaintEtienne",
    "#Association",
    "#Revitalisation",
    "#Territoires",
    "#Reemploi",
    "#EconomieCirculaire"
  ]
}